tigrinya_nlp/__init__.py
tigrinya_nlp/cleaning.py
tigrinya_nlp/normalization.py
tigrinya_nlp/stopwords.py
tigrinya_nlp/tokenization.py
tigrinya_nlp/utils.py
tigrinya_nlp-0.1.1.dist-info/METADATA
tigrinya_nlp-0.1.1.dist-info/WHEEL
tigrinya_nlp-0.1.1.dist-info/licenses/LICENSE
tigrinya_nlp-0.1.1.dist-info/RECORD
