Metadata-Version: 2.4
Name: tigrinya-nlp
Version: 0.1.1
Summary: Lightweight Tigrinya text preprocessing: normalization, cleaning, tokenization, and stopwords.
Project-URL: Homepage, https://github.com/makda-tsegazeab/tigrinya-nlp
Project-URL: Repository, https://github.com/makda-tsegazeab/tigrinya-nlp
Project-URL: Issues, https://github.com/makda-tsegazeab/tigrinya-nlp/issues
Author-email: Makda Tsegazeab Mammo <makdamammo99@gmail.com>
License: MIT License
License-File: LICENSE
Keywords: ethiopic,nlp,normalization,text-processing,tigrinya,tokenization
Classifier: Development Status :: 3 - Alpha
Classifier: Intended Audience :: Developers
Classifier: Intended Audience :: Science/Research
Classifier: License :: OSI Approved :: MIT License
Classifier: Natural Language :: English
Classifier: Programming Language :: Python :: 3
Classifier: Programming Language :: Python :: 3.10
Classifier: Programming Language :: Python :: 3.11
Classifier: Programming Language :: Python :: 3.12
Classifier: Programming Language :: Python :: 3.13
Classifier: Topic :: Software Development :: Libraries :: Python Modules
Classifier: Topic :: Text Processing :: Linguistic
Requires-Python: >=3.10
Provides-Extra: dev
Requires-Dist: build>=1.2; extra == 'dev'
Requires-Dist: mypy>=1.10; extra == 'dev'
Requires-Dist: pytest-cov>=5.0; extra == 'dev'
Requires-Dist: pytest>=8.0; extra == 'dev'
Requires-Dist: ruff>=0.6.0; extra == 'dev'
Requires-Dist: twine>=5.0; extra == 'dev'
